test/__init__.py
test/example.py
wto/__init__.py
wto/time_series_datapoints.py
wto-0.1.1.dist-info/LICENSE
wto-0.1.1.dist-info/METADATA
wto-0.1.1.dist-info/WHEEL
wto-0.1.1.dist-info/top_level.txt
wto-0.1.1.dist-info/RECORD
