Metadata-Version: 2.1
Name: wto
Version: 0.1.1
Summary: A Python library to query the WTO's API
Home-page: https://github.com/LaRocca89/wto_data_puller
Author: Greg LaRocca
Author-email: larocca89@gmail.com
License: UNKNOWN
Platform: UNKNOWN
Classifier: Programming Language :: Python :: 3
Classifier: License :: OSI Approved :: MIT License
Classifier: Operating System :: OS Independent
Requires-Python: >=3.6
Requires-Dist: requests
